fofunction/__init__.py
fofunction/axis.py
fofunction/curve.py
fofunction/function.py
fofunction/log.py
fofunction/map.py
fofunction/value.py
fofunction-0.5.0.dist-info/LICENSE.txt
fofunction-0.5.0.dist-info/METADATA
fofunction-0.5.0.dist-info/WHEEL
fofunction-0.5.0.dist-info/top_level.txt
fofunction-0.5.0.dist-info/RECORD
