Metadata-Version: 2.1
Name: fofunction
Version: 0.5.0
Summary: Far-Out Control Unit function
Home-page: https://gitlab.com/far-out/fofunction.git
Author: Jerome Douay
Author-email: jerome@far-out.biz
License: MIT
Project-URL: Documentation, https://pyscaffold.org/
Platform: any
Classifier: Development Status :: 4 - Beta
Classifier: Programming Language :: Python
License-File: LICENSE.txt
Requires-Dist: foextract
Requires-Dist: importlib-metadata ; python_version < "3.8"
Provides-Extra: testing
Requires-Dist: setuptools ; extra == 'testing'
Requires-Dist: pytest ; extra == 'testing'
Requires-Dist: pytest-cov ; extra == 'testing'
